odoo/addons/mis_builder_pms/README.rst
odoo/addons/mis_builder_pms/__init__.py
odoo/addons/mis_builder_pms/__manifest__.py
odoo/addons/mis_builder_pms/i18n/it.po
odoo/addons/mis_builder_pms/i18n/mis_builder_pms.pot
odoo/addons/mis_builder_pms/models/__init__.py
odoo/addons/mis_builder_pms/models/mis_builder.py
odoo/addons/mis_builder_pms/readme/CONTRIBUTORS.rst
odoo/addons/mis_builder_pms/readme/DESCRIPTION.rst
odoo/addons/mis_builder_pms/readme/USAGE.rst
odoo/addons/mis_builder_pms/static/description/icon.png
odoo/addons/mis_builder_pms/static/description/index.html
odoo/addons/mis_builder_pms/static/src/js/mis_report_widget.js
odoo/addons/mis_builder_pms/views/mis_builder_view.xml
odoo14_addon_mis_builder_pms-14.0.1.0.1.dev5.dist-info/METADATA
odoo14_addon_mis_builder_pms-14.0.1.0.1.dev5.dist-info/WHEEL
odoo14_addon_mis_builder_pms-14.0.1.0.1.dev5.dist-info/top_level.txt
odoo14_addon_mis_builder_pms-14.0.1.0.1.dev5.dist-info/RECORD
